playertracer/__init__.py
playertracer/playertracer.py
PlayerTracer-0.0.1.dist-info/LICENSE
PlayerTracer-0.0.1.dist-info/METADATA
PlayerTracer-0.0.1.dist-info/WHEEL
PlayerTracer-0.0.1.dist-info/top_level.txt
PlayerTracer-0.0.1.dist-info/RECORD
