Metadata-Version: 2.1
Name: PlayerTracer
Version: 0.0.1
Summary: Insert project description here
Author: Hendrik du Toit
Author-email: hendrik@brightedge.co.za
Classifier: Development Status :: 1 - Planning
Classifier: Intended Audience :: Developers
Classifier: Topic :: Software Development
Classifier: License :: OSI Approved :: MIT License
Classifier: Programming Language :: Python :: 3.0
Classifier: Programming Language :: Python :: 3.6
Classifier: Programming Language :: Python :: 3.7
Classifier: Programming Language :: Python :: 3.8
Classifier: Programming Language :: Python :: 3.9
Classifier: Programming Language :: Python :: 3.10
License-File: LICENSE
Requires-Dist: beetools
Requires-Dist: configparserext
Requires-Dist: releaselogit
Requires-Dist: semverit
Requires-Dist: termcolor
Requires-Dist: toml
